{"collection":{"item":[{"name":"api","description":"","item":[{"name":"User","description":"","item":[{"name":"GetLatestTaC","description":"","item":[{"id":"ea12b935-1d96-4385-acf1-3831c9737268","name":"Latest Ta C Response","request":{"name":"Latest Ta C Response","description":{"content":"This endpoint will get the TaC Version.","type":"text/plain"},"url":{"path":["api","User","GetLatestTaC"],"host":["{{baseUrl}}"],"query":[{"disabled":false,"description":{"content":"(Required) ","type":"text/plain"},"key":"UserId","value":"<string>"}],"variable":[]},"header":[{"key":"Accept","value":"application/json"}],"method":"GET","body":{},"auth":null},"response":[{"id":"eb7bb3d0-e586-42c0-bfd3-63a2a6a4bcb3","name":"Response","originalRequest":{"url":{"path":["api","User","GetLatestTaC"],"host":["{{baseUrl}}"],"query":[{"disabled":false,"description":{"content":"(Required) ","type":"text/plain"},"key":"UserId","value":"<string>"}],"variable":[]},"header":[{"key":"Accept","value":"application/json"}],"method":"GET","body":{}},"status":"OK","code":200,"header":[{"key":"Content-Type","value":"application/json"}],"body":"{\n  \"acceptDate\": \"<string>\",\n  \"version\": \"<string>\"\n}","cookie":[],"_postman_previewlanguage":"json"}],"event":[],"protocolProfileBehavior":{"disableBodyPruning":true}}]},{"name":"AddTaCVersion","description":"","item":[{"id":"16d23028-75bf-4317-b07d-a2bbeeb08335","name":"Add Ta C Version Response","request":{"name":"Add Ta C Version Response","description":{"content":"This endpoint will accept the TaC Version.","type":"text/plain"},"url":{"path":["api","User","AddTaCVersion"],"host":["{{baseUrl}}"],"query":[],"variable":[]},"header":[{"key":"Content-Type","value":"application/json"},{"key":"Accept","value":"application/json"}],"method":"POST","body":{"mode":"raw","raw":"{\n  \"taCVersion\": \"<string>\",\n  \"userId\": \"<string>\"\n}","options":{"raw":{"headerFamily":"json","language":"json"}}},"auth":null},"response":[{"id":"1d1337f5-2a81-46dd-aa15-37a8e25587ae","name":"Response","originalRequest":{"url":{"path":["api","User","AddTaCVersion"],"host":["{{baseUrl}}"],"query":[],"variable":[]},"header":[{"key":"Content-Type","value":"application/json"},{"key":"Accept","value":"application/json"}],"method":"POST","body":{"mode":"raw","raw":"{\n  \"taCVersion\": \"<string>\",\n  \"userId\": \"<string>\"\n}","options":{"raw":{"headerFamily":"json","language":"json"}}}},"status":"OK","code":200,"header":[{"key":"Content-Type","value":"application/json"}],"body":"{\n  \"successfulAccept\": \"<boolean>\"\n}","cookie":[],"_postman_previewlanguage":"json"}],"event":[],"protocolProfileBehavior":{"disableBodyPruning":true}}]}]},{"name":"Nethone","description":"","item":[{"name":"NethoneTransactionConfirm","description":"","item":[{"id":"046e1ae2-bcf7-432a-b5f7-47e76eec5e0e","name":"NethoneTransactionConfirm: Validates Nethone transaction integrity","request":{"name":"NethoneTransactionConfirm: Validates Nethone transaction integrity","description":{},"url":{"path":["api","Nethone","NethoneTransactionConfirm"],"host":["{{baseUrl}}"],"query":[],"variable":[]},"header":[{"key":"Content-Type","value":"application/json"},{"key":"Accept","value":"application/json"}],"method":"PUT","body":{"mode":"raw","raw":"{\n  \"id\": \"<long>\",\n  \"flags\": [\n    {\n      \"timestamp\": \"<string>\",\n      \"name\": \"<string>\",\n      \"value\": \"<boolean>\"\n    },\n    {\n      \"timestamp\": \"<string>\",\n      \"name\": \"<string>\",\n      \"value\": \"<boolean>\"\n    }\n  ]\n}","options":{"raw":{"headerFamily":"json","language":"json"}}},"auth":null},"response":[{"id":"2afbb5a6-5bbf-41f4-8a99-00453d0207a5","name":"Returns payment token information.","originalRequest":{"url":{"path":["api","Nethone","NethoneTransactionConfirm"],"host":["{{baseUrl}}"],"query":[],"variable":[]},"header":[{"key":"Content-Type","value":"application/json"},{"key":"Accept","value":"application/json"}],"method":"PUT","body":{"mode":"raw","raw":"{\n  \"id\": \"<long>\",\n  \"flags\": [\n    {\n      \"timestamp\": \"<string>\",\n      \"name\": \"<string>\",\n      \"value\": \"<boolean>\"\n    },\n    {\n      \"timestamp\": \"<string>\",\n      \"name\": \"<string>\",\n      \"value\": \"<boolean>\"\n    }\n  ]\n}","options":{"raw":{"headerFamily":"json","language":"json"}}}},"status":"OK","code":200,"header":[{"key":"Content-Type","value":"application/json"}],"body":"{\n  \"id\": \"<long>\",\n  \"id_str\": \"<string>\",\n  \"reference\": \"<string>\"\n}","cookie":[],"_postman_previewlanguage":"json"},{"id":"ae8571ab-be04-4103-99c8-009e2aa341d3","name":"Unauthorized","originalRequest":{"url":{"path":["api","Nethone","NethoneTransactionConfirm"],"host":["{{baseUrl}}"],"query":[],"variable":[]},"header":[{"key":"Content-Type","value":"application/json"},{"key":"Accept","value":"application/json"}],"method":"PUT","body":{"mode":"raw","raw":"{\n  \"id\": \"<long>\",\n  \"flags\": [\n    {\n      \"timestamp\": \"<string>\",\n      \"name\": \"<string>\",\n      \"value\": \"<boolean>\"\n    },\n    {\n      \"timestamp\": \"<string>\",\n      \"name\": \"<string>\",\n      \"value\": \"<boolean>\"\n    }\n  ]\n}","options":{"raw":{"headerFamily":"json","language":"json"}}}},"status":"Unauthorized","code":401,"header":[{"key":"Content-Type","value":"application/json"}],"body":"{\n  \"type\": \"<string>\",\n  \"title\": \"<string>\",\n  \"status\": \"<integer>\",\n  \"detail\": \"<string>\",\n  \"instance\": \"<string>\",\n  \"dolore5\": {}\n}","cookie":[],"_postman_previewlanguage":"json"},{"id":"5998f0e9-76cd-4a44-813e-8f7285cae267","name":"Auth0 error,validate the error log.","originalRequest":{"url":{"path":["api","Nethone","NethoneTransactionConfirm"],"host":["{{baseUrl}}"],"query":[],"variable":[]},"header":[{"key":"Content-Type","value":"application/json"},{"key":"Accept","value":"application/json"}],"method":"PUT","body":{"mode":"raw","raw":"{\n  \"id\": \"<long>\",\n  \"flags\": [\n    {\n      \"timestamp\": \"<string>\",\n      \"name\": \"<string>\",\n      \"value\": \"<boolean>\"\n    },\n    {\n      \"timestamp\": \"<string>\",\n      \"name\": \"<string>\",\n      \"value\": \"<boolean>\"\n    }\n  ]\n}","options":{"raw":{"headerFamily":"json","language":"json"}}}},"status":"Payment Required","code":402,"header":[{"key":"Content-Type","value":"application/json"}],"body":"{\n  \"type\": \"<string>\",\n  \"title\": \"<string>\",\n  \"status\": \"<integer>\",\n  \"detail\": \"<string>\",\n  \"instance\": \"<string>\",\n  \"dolore5\": {}\n}","cookie":[],"_postman_previewlanguage":"json"},{"id":"8ee3d4cb-9f19-4098-9414-b1b51d88b8b5","name":"Unhandled error, validate the error log.","originalRequest":{"url":{"path":["api","Nethone","NethoneTransactionConfirm"],"host":["{{baseUrl}}"],"query":[],"variable":[]},"header":[{"key":"Content-Type","value":"application/json"},{"key":"Accept","value":"application/json"}],"method":"PUT","body":{"mode":"raw","raw":"{\n  \"id\": \"<long>\",\n  \"flags\": [\n    {\n      \"timestamp\": \"<string>\",\n      \"name\": \"<string>\",\n      \"value\": \"<boolean>\"\n    },\n    {\n      \"timestamp\": \"<string>\",\n      \"name\": \"<string>\",\n      \"value\": \"<boolean>\"\n    }\n  ]\n}","options":{"raw":{"headerFamily":"json","language":"json"}}}},"status":"Not Found","code":404,"header":[{"key":"Content-Type","value":"application/json"}],"body":"{\n  \"type\": \"<string>\",\n  \"title\": \"<string>\",\n  \"status\": \"<integer>\",\n  \"detail\": \"<string>\",\n  \"instance\": \"<string>\",\n  \"dolore5\": {}\n}","cookie":[],"_postman_previewlanguage":"json"}],"event":[],"protocolProfileBehavior":{"disableBodyPruning":true}}]},{"name":"NethoneTransaction","description":"","item":[{"id":"2120c730-8a80-49ce-9378-66eeb8b73be3","name":"NethoneTransaction: Process Nethone transaction","request":{"name":"NethoneTransaction: Process Nethone transaction","description":{},"url":{"path":["api","Nethone","NethoneTransaction"],"host":["{{baseUrl}}"],"query":[],"variable":[]},"header":[{"key":"Content-Type","value":"application/json"},{"key":"Accept","value":"application/json"}],"method":"POST","body":{"mode":"raw","raw":"{\n  \"reference\": \"<string>\",\n  \"merchant_reference\": \"<string>\",\n  \"payment_method\": \"<string>\",\n  \"user_reference\": \"<string>\",\n  \"profiling_reference\": \"<string>\",\n  \"timestamp\": \"<string>\",\n  \"currency\": \"<string>\",\n  \"amount\": \"<string>\",\n  \"card_token\": \"<string>\",\n  \"flags\": [\n    {\n      \"timestamp\": \"<string>\",\n      \"name\": \"<string>\",\n      \"value\": \"<boolean>\"\n    },\n    {\n      \"timestamp\": \"<string>\",\n      \"name\": \"<string>\",\n      \"value\": \"<boolean>\"\n    }\n  ],\n  \"inquiry_id\": \"<long>\"\n}","options":{"raw":{"headerFamily":"json","language":"json"}}},"auth":null},"response":[{"id":"13dcc3a0-beca-4eaf-b5ee-93db278b0762","name":"Returns payment token information.","originalRequest":{"url":{"path":["api","Nethone","NethoneTransaction"],"host":["{{baseUrl}}"],"query":[],"variable":[]},"header":[{"key":"Content-Type","value":"application/json"},{"key":"Accept","value":"application/json"}],"method":"POST","body":{"mode":"raw","raw":"{\n  \"reference\": \"<string>\",\n  \"merchant_reference\": \"<string>\",\n  \"payment_method\": \"<string>\",\n  \"user_reference\": \"<string>\",\n  \"profiling_reference\": \"<string>\",\n  \"timestamp\": \"<string>\",\n  \"currency\": \"<string>\",\n  \"amount\": \"<string>\",\n  \"card_token\": \"<string>\",\n  \"flags\": [\n    {\n      \"timestamp\": \"<string>\",\n      \"name\": \"<string>\",\n      \"value\": \"<boolean>\"\n    },\n    {\n      \"timestamp\": \"<string>\",\n      \"name\": \"<string>\",\n      \"value\": \"<boolean>\"\n    }\n  ],\n  \"inquiry_id\": \"<long>\"\n}","options":{"raw":{"headerFamily":"json","language":"json"}}}},"status":"OK","code":200,"header":[{"key":"Content-Type","value":"application/json"}],"body":"{\n  \"id\": \"<long>\",\n  \"id_str\": \"<string>\",\n  \"reference\": \"<string>\"\n}","cookie":[],"_postman_previewlanguage":"json"},{"id":"06f6b4f0-5b10-4e83-9e22-c2da620146b8","name":"Unauthorized","originalRequest":{"url":{"path":["api","Nethone","NethoneTransaction"],"host":["{{baseUrl}}"],"query":[],"variable":[]},"header":[{"key":"Content-Type","value":"application/json"},{"key":"Accept","value":"application/json"}],"method":"POST","body":{"mode":"raw","raw":"{\n  \"reference\": \"<string>\",\n  \"merchant_reference\": \"<string>\",\n  \"payment_method\": \"<string>\",\n  \"user_reference\": \"<string>\",\n  \"profiling_reference\": \"<string>\",\n  \"timestamp\": \"<string>\",\n  \"currency\": \"<string>\",\n  \"amount\": \"<string>\",\n  \"card_token\": \"<string>\",\n  \"flags\": [\n    {\n      \"timestamp\": \"<string>\",\n      \"name\": \"<string>\",\n      \"value\": \"<boolean>\"\n    },\n    {\n      \"timestamp\": \"<string>\",\n      \"name\": \"<string>\",\n      \"value\": \"<boolean>\"\n    }\n  ],\n  \"inquiry_id\": \"<long>\"\n}","options":{"raw":{"headerFamily":"json","language":"json"}}}},"status":"Unauthorized","code":401,"header":[{"key":"Content-Type","value":"application/json"}],"body":"{\n  \"type\": \"<string>\",\n  \"title\": \"<string>\",\n  \"status\": \"<integer>\",\n  \"detail\": \"<string>\",\n  \"instance\": \"<string>\",\n  \"dolore5\": {}\n}","cookie":[],"_postman_previewlanguage":"json"},{"id":"1a7b46ed-2a3b-4767-8bbd-857e8ee2931f","name":"Auth0 error,validate the error log.","originalRequest":{"url":{"path":["api","Nethone","NethoneTransaction"],"host":["{{baseUrl}}"],"query":[],"variable":[]},"header":[{"key":"Content-Type","value":"application/json"},{"key":"Accept","value":"application/json"}],"method":"POST","body":{"mode":"raw","raw":"{\n  \"reference\": \"<string>\",\n  \"merchant_reference\": \"<string>\",\n  \"payment_method\": \"<string>\",\n  \"user_reference\": \"<string>\",\n  \"profiling_reference\": \"<string>\",\n  \"timestamp\": \"<string>\",\n  \"currency\": \"<string>\",\n  \"amount\": \"<string>\",\n  \"card_token\": \"<string>\",\n  \"flags\": [\n    {\n      \"timestamp\": \"<string>\",\n      \"name\": \"<string>\",\n      \"value\": \"<boolean>\"\n    },\n    {\n      \"timestamp\": \"<string>\",\n      \"name\": \"<string>\",\n      \"value\": \"<boolean>\"\n    }\n  ],\n  \"inquiry_id\": \"<long>\"\n}","options":{"raw":{"headerFamily":"json","language":"json"}}}},"status":"Payment Required","code":402,"header":[{"key":"Content-Type","value":"application/json"}],"body":"{\n  \"type\": \"<string>\",\n  \"title\": \"<string>\",\n  \"status\": \"<integer>\",\n  \"detail\": \"<string>\",\n  \"instance\": \"<string>\",\n  \"dolore5\": {}\n}","cookie":[],"_postman_previewlanguage":"json"},{"id":"bcbf6c61-cfb4-4b8c-859d-11c04e38d849","name":"Unhandled error, validate the error log.","originalRequest":{"url":{"path":["api","Nethone","NethoneTransaction"],"host":["{{baseUrl}}"],"query":[],"variable":[]},"header":[{"key":"Content-Type","value":"application/json"},{"key":"Accept","value":"application/json"}],"method":"POST","body":{"mode":"raw","raw":"{\n  \"reference\": \"<string>\",\n  \"merchant_reference\": \"<string>\",\n  \"payment_method\": \"<string>\",\n  \"user_reference\": \"<string>\",\n  \"profiling_reference\": \"<string>\",\n  \"timestamp\": \"<string>\",\n  \"currency\": \"<string>\",\n  \"amount\": \"<string>\",\n  \"card_token\": \"<string>\",\n  \"flags\": [\n    {\n      \"timestamp\": \"<string>\",\n      \"name\": \"<string>\",\n      \"value\": \"<boolean>\"\n    },\n    {\n      \"timestamp\": \"<string>\",\n      \"name\": \"<string>\",\n      \"value\": \"<boolean>\"\n    }\n  ],\n  \"inquiry_id\": \"<long>\"\n}","options":{"raw":{"headerFamily":"json","language":"json"}}}},"status":"Not Found","code":404,"header":[{"key":"Content-Type","value":"application/json"}],"body":"{\n  \"type\": \"<string>\",\n  \"title\": \"<string>\",\n  \"status\": \"<integer>\",\n  \"detail\": \"<string>\",\n  \"instance\": \"<string>\",\n  \"dolore5\": {}\n}","cookie":[],"_postman_previewlanguage":"json"}],"event":[],"protocolProfileBehavior":{"disableBodyPruning":true}}]},{"name":"NethoneRecommendationPay","description":"","item":[{"id":"7ac636eb-f5c2-4c2f-a14f-ad045f351fe1","name":"NethoneRecommendationPay: check if the data has suspicious or fraudulent activity","request":{"name":"NethoneRecommendationPay: check if the data has suspicious or fraudulent activity","description":{},"url":{"path":["api","Nethone","NethoneRecommendationPay"],"host":["{{baseUrl}}"],"query":[{"disabled":false,"description":{"content":"Object with data new card","type":"text/plain"},"key":"ObjNewCardRequest","value":"<string>"}],"variable":[]},"header":[{"key":"Accept","value":"application/json"}],"method":"POST","body":{},"auth":null},"response":[{"id":"258ef1a4-535b-40cf-8c15-327f562de164","name":"Success","originalRequest":{"url":{"path":["api","Nethone","NethoneRecommendationPay"],"host":["{{baseUrl}}"],"query":[{"disabled":false,"description":{"content":"Object with data new card","type":"text/plain"},"key":"ObjNewCardRequest","value":"<string>"}],"variable":[]},"header":[{"key":"Accept","value":"application/json"}],"method":"POST","body":{}},"status":"OK","code":200,"header":[{"key":"Content-Type","value":"application/json"}],"body":"{\n  \"id\": \"<long>\",\n  \"id_str\": \"<string>\",\n  \"advice\": \"<string>\",\n  \"info\": {\n    \"fingerprint\": {\n      \"signals\": [\n        \"<string>\",\n        \"<string>\"\n      ],\n      \"profiling_type\": \"<string>\",\n      \"attempt_reference\": \"<string>\",\n      \"created_date\": \"<string>\",\n      \"ip\": \"<string>\",\n      \"network\": {\n        \"link_type\": \"<string>\",\n        \"user_declared_ip\": {\n          \"addr\": \"<string>\"\n        }\n      },\n      \"device\": {\n        \"carrier\": {\n          \"name\": \"<string>\",\n          \"country\": \"<string>\",\n          \"iso_country_code\": \"<string>\",\n          \"mobile_country_code\": \"<string>\",\n          \"mobile_network_code\": \"<string>\",\n          \"allows_voip\": \"<boolean>\",\n          \"icc_card\": \"<boolean>\",\n          \"roaming\": \"<boolean>\",\n          \"sim_state\": \"<integer>\",\n          \"radio_phone_type\": \"<integer>\",\n          \"network_type\": \"<string>\"\n        },\n        \"disk\": {\n          \"mobile_network_code\": \"<string>\",\n          \"free_space_root\": \"<string>\"\n        },\n        \"device\": {\n          \"android_id\": \"<string>\",\n          \"model\": \"<string>\",\n          \"manufacturer\": \"<string>\",\n          \"brand\": \"<string>\",\n          \"build_fingerprint\": \"<string>\",\n          \"product\": \"<string>\",\n          \"http_proxy\": \"<string>\",\n          \"wifi_on\": \"<boolean>\",\n          \"bt_on\": \"<boolean>\",\n          \"uptime_ms\": \"<string>\"\n        },\n        \"battery\": {\n          \"battery_health\": \"<string>\",\n          \"extra_health\": \"<integer>\",\n          \"levelextra_status\": \"<double>\",\n          \"extra_level\": \"<integer>\",\n          \"extra_scale_level\": \"<integer>\",\n          \"battery\": \"<string>\",\n          \"extra_plugged\": \"<integer>\",\n          \"charging_state\": \"<string>\",\n          \"extra_status\": \"<integer>\",\n          \"extra_present\": \"<boolean>\",\n          \"extra_technology\": \"<string>\",\n          \"extra_temperature\": \"<integer>\",\n          \"extra_voltage\": \"<integer>\"\n        }\n      }\n    },\n    \"rules\": [\n      {\n        \"id\": \"<long>\",\n        \"id_str\": \"<string>\",\n        \"name\": \"<string>\",\n        \"advice\": \"<string>\",\n        \"mode\": \"<string>\"\n      },\n      {\n        \"id\": \"<long>\",\n        \"id_str\": \"<string>\",\n        \"name\": \"<string>\",\n        \"advice\": \"<string>\",\n        \"mode\": \"<string>\"\n      }\n    ]\n  }\n}","cookie":[],"_postman_previewlanguage":"json"}],"event":[],"protocolProfileBehavior":{"disableBodyPruning":true}}]},{"name":"NethoneRecommendation","description":"","item":[{"id":"6bc8c9c0-647a-4eaa-9e6d-0b9c007de5b8","name":"NethoneRecommendation: Process Nethone recommendation","request":{"name":"NethoneRecommendation: Process Nethone recommendation","description":{},"url":{"path":["api","Nethone","NethoneRecommendation"],"host":["{{baseUrl}}"],"query":[],"variable":[]},"header":[{"key":"Content-Type","value":"application/json"},{"key":"Accept","value":"application/json"}],"method":"POST","body":{"mode":"raw","raw":"{\n  \"userId\": \"<string>\",\n  \"attemptReference\": \"<string>\",\n  \"inquiryType\": \"<string>\",\n  \"eventType\": \"<string>\",\n  \"deviceId\": \"<string>\",\n  \"requiredEvent\": \"<boolean>\"\n}","options":{"raw":{"headerFamily":"json","language":"json"}}},"auth":null},"response":[{"id":"34019ad8-0596-4aa7-864a-dd9a2a9ad01c","name":"Returns payment token information.","originalRequest":{"url":{"path":["api","Nethone","NethoneRecommendation"],"host":["{{baseUrl}}"],"query":[],"variable":[]},"header":[{"key":"Content-Type","value":"application/json"},{"key":"Accept","value":"application/json"}],"method":"POST","body":{"mode":"raw","raw":"{\n  \"userId\": \"<string>\",\n  \"attemptReference\": \"<string>\",\n  \"inquiryType\": \"<string>\",\n  \"eventType\": \"<string>\",\n  \"deviceId\": \"<string>\",\n  \"requiredEvent\": \"<boolean>\"\n}","options":{"raw":{"headerFamily":"json","language":"json"}}}},"status":"OK","code":200,"header":[{"key":"Content-Type","value":"application/json"}],"body":"{\n  \"id\": \"<long>\",\n  \"id_str\": \"<string>\",\n  \"advice\": \"<string>\",\n  \"info\": {\n    \"fingerprint\": {\n      \"signals\": [\n        \"<string>\",\n        \"<string>\"\n      ],\n      \"profiling_type\": \"<string>\",\n      \"attempt_reference\": \"<string>\",\n      \"created_date\": \"<string>\",\n      \"ip\": \"<string>\",\n      \"network\": {\n        \"link_type\": \"<string>\",\n        \"user_declared_ip\": {\n          \"addr\": \"<string>\"\n        }\n      },\n      \"device\": {\n        \"carrier\": {\n          \"name\": \"<string>\",\n          \"country\": \"<string>\",\n          \"iso_country_code\": \"<string>\",\n          \"mobile_country_code\": \"<string>\",\n          \"mobile_network_code\": \"<string>\",\n          \"allows_voip\": \"<boolean>\",\n          \"icc_card\": \"<boolean>\",\n          \"roaming\": \"<boolean>\",\n          \"sim_state\": \"<integer>\",\n          \"radio_phone_type\": \"<integer>\",\n          \"network_type\": \"<string>\"\n        },\n        \"disk\": {\n          \"mobile_network_code\": \"<string>\",\n          \"free_space_root\": \"<string>\"\n        },\n        \"device\": {\n          \"android_id\": \"<string>\",\n          \"model\": \"<string>\",\n          \"manufacturer\": \"<string>\",\n          \"brand\": \"<string>\",\n          \"build_fingerprint\": \"<string>\",\n          \"product\": \"<string>\",\n          \"http_proxy\": \"<string>\",\n          \"wifi_on\": \"<boolean>\",\n          \"bt_on\": \"<boolean>\",\n          \"uptime_ms\": \"<string>\"\n        },\n        \"battery\": {\n          \"battery_health\": \"<string>\",\n          \"extra_health\": \"<integer>\",\n          \"levelextra_status\": \"<double>\",\n          \"extra_level\": \"<integer>\",\n          \"extra_scale_level\": \"<integer>\",\n          \"battery\": \"<string>\",\n          \"extra_plugged\": \"<integer>\",\n          \"charging_state\": \"<string>\",\n          \"extra_status\": \"<integer>\",\n          \"extra_present\": \"<boolean>\",\n          \"extra_technology\": \"<string>\",\n          \"extra_temperature\": \"<integer>\",\n          \"extra_voltage\": \"<integer>\"\n        }\n      }\n    },\n    \"rules\": [\n      {\n        \"id\": \"<long>\",\n        \"id_str\": \"<string>\",\n        \"name\": \"<string>\",\n        \"advice\": \"<string>\",\n        \"mode\": \"<string>\"\n      },\n      {\n        \"id\": \"<long>\",\n        \"id_str\": \"<string>\",\n        \"name\": \"<string>\",\n        \"advice\": \"<string>\",\n        \"mode\": \"<string>\"\n      }\n    ]\n  }\n}","cookie":[],"_postman_previewlanguage":"json"},{"id":"987a29a7-a776-497e-9d39-936ef65313b5","name":"Unauthorized","originalRequest":{"url":{"path":["api","Nethone","NethoneRecommendation"],"host":["{{baseUrl}}"],"query":[],"variable":[]},"header":[{"key":"Content-Type","value":"application/json"},{"key":"Accept","value":"application/json"}],"method":"POST","body":{"mode":"raw","raw":"{\n  \"userId\": \"<string>\",\n  \"attemptReference\": \"<string>\",\n  \"inquiryType\": \"<string>\",\n  \"eventType\": \"<string>\",\n  \"deviceId\": \"<string>\",\n  \"requiredEvent\": \"<boolean>\"\n}","options":{"raw":{"headerFamily":"json","language":"json"}}}},"status":"Unauthorized","code":401,"header":[{"key":"Content-Type","value":"application/json"}],"body":"{\n  \"type\": \"<string>\",\n  \"title\": \"<string>\",\n  \"status\": \"<integer>\",\n  \"detail\": \"<string>\",\n  \"instance\": \"<string>\",\n  \"dolore5\": {}\n}","cookie":[],"_postman_previewlanguage":"json"},{"id":"f7c02738-7ae6-4194-9449-06923fac4bdd","name":"Auth0 error,validate the error log.","originalRequest":{"url":{"path":["api","Nethone","NethoneRecommendation"],"host":["{{baseUrl}}"],"query":[],"variable":[]},"header":[{"key":"Content-Type","value":"application/json"}],"method":"POST","body":{"mode":"raw","raw":"{\n  \"userId\": \"<string>\",\n  \"attemptReference\": \"<string>\",\n  \"inquiryType\": \"<string>\",\n  \"eventType\": \"<string>\",\n  \"deviceId\": \"<string>\",\n  \"requiredEvent\": \"<boolean>\"\n}","options":{"raw":{"headerFamily":"json","language":"json"}}}},"status":"Payment Required","code":402,"header":[],"cookie":[],"_postman_previewlanguage":"text"},{"id":"89b34304-5925-4d13-aae6-fefda1b80388","name":"Unhandled error, validate the error log.","originalRequest":{"url":{"path":["api","Nethone","NethoneRecommendation"],"host":["{{baseUrl}}"],"query":[],"variable":[]},"header":[{"key":"Content-Type","value":"application/json"},{"key":"Accept","value":"application/json"}],"method":"POST","body":{"mode":"raw","raw":"{\n  \"userId\": \"<string>\",\n  \"attemptReference\": \"<string>\",\n  \"inquiryType\": \"<string>\",\n  \"eventType\": \"<string>\",\n  \"deviceId\": \"<string>\",\n  \"requiredEvent\": \"<boolean>\"\n}","options":{"raw":{"headerFamily":"json","language":"json"}}}},"status":"Not Found","code":404,"header":[{"key":"Content-Type","value":"application/json"}],"body":"{\n  \"type\": \"<string>\",\n  \"title\": \"<string>\",\n  \"status\": \"<integer>\",\n  \"detail\": \"<string>\",\n  \"instance\": \"<string>\",\n  \"dolore5\": {}\n}","cookie":[],"_postman_previewlanguage":"json"}],"event":[],"protocolProfileBehavior":{"disableBodyPruning":true}}]}]},{"name":"Health","description":"","item":[{"name":"Health","description":"","item":[{"id":"f0a7bedc-7368-4518-aa94-41c9871c01bb","name":"/api/Health/Health","request":{"name":"/api/Health/Health","description":{},"url":{"path":["api","Health","Health"],"host":["{{baseUrl}}"],"query":[],"variable":[]},"method":"GET","body":{},"auth":null},"response":[{"id":"3183d42c-18fd-4e6b-92e7-7d720bb652ae","name":"Returns a 200 if the API is online.","originalRequest":{"url":{"path":["api","Health","Health"],"host":["{{baseUrl}}"],"query":[],"variable":[]},"method":"GET","body":{}},"status":"OK","code":200,"header":[],"cookie":[],"_postman_previewlanguage":"text"},{"id":"14e87c9a-0cf1-4ccb-af5b-767ce4e958f7","name":"Unhandled error, validate the error log.","originalRequest":{"url":{"path":["api","Health","Health"],"host":["{{baseUrl}}"],"query":[],"variable":[]},"method":"GET","body":{}},"status":"Internal Server Error","code":500,"header":[],"cookie":[],"_postman_previewlanguage":"text"}],"event":[],"protocolProfileBehavior":{"disableBodyPruning":true}}]}]},{"name":"Auth","description":"","item":[{"name":"UserValidation","description":"","item":[{"id":"bc87c4ce-08e2-40c2-9653-414b78eb4ad6","name":"User Validation","request":{"name":"User Validation","description":{"content":"This endpoint will validate if the user has any of the following states: \n\t\t\t\t\t\t\t\t\t\t\t   <ul><li>NotRegistered = 0</li><li>PreRegistered = 1</li><li>Registered = 2</li>\n\t\t\t\t\t\t\t\t\t\t\t   <li>OTPRequired = 3</li><li>SoftBlock = 4</li><li>HardBlock = 5</li>\n\t\t\t\t\t\t\t\t\t\t\t   <li>CancelledAccount = 8</li><li>FirstLoginOxxo = 20</li></ul>","type":"text/plain"},"url":{"path":["api","Auth","UserValidation"],"host":["{{baseUrl}}"],"query":[{"disabled":false,"description":{"content":"(Required) ","type":"text/plain"},"key":"PhoneNumber","value":"<string>"},{"disabled":false,"description":{"content":"(Required) ","type":"text/plain"},"key":"DeviceId","value":"<string>"},{"disabled":false,"description":{"content":"","type":"text/plain"},"key":"AttemptReference","value":"<string>"}],"variable":[]},"header":[{"key":"Accept","value":"application/json"}],"method":"GET","body":{},"auth":null},"response":[{"id":"bd70fb0a-8183-45bc-9bde-afa47056b476","name":"Response","originalRequest":{"url":{"path":["api","Auth","UserValidation"],"host":["{{baseUrl}}"],"query":[{"disabled":false,"description":{"content":"(Required) ","type":"text/plain"},"key":"PhoneNumber","value":"<string>"},{"disabled":false,"description":{"content":"(Required) ","type":"text/plain"},"key":"DeviceId","value":"<string>"},{"disabled":false,"description":{"content":"","type":"text/plain"},"key":"AttemptReference","value":"<string>"}],"variable":[]},"header":[{"key":"Accept","value":"application/json"}],"method":"GET","body":{}},"status":"OK","code":200,"header":[{"key":"Content-Type","value":"application/json"}],"body":"{\n  \"codeUserStatus\": \"<string>\"\n}","cookie":[],"_postman_previewlanguage":"json"},{"id":"7bd842c5-68d9-4b97-bb66-08a4063ea558","name":"SPCI-404: User not found","originalRequest":{"url":{"path":["api","Auth","UserValidation"],"host":["{{baseUrl}}"],"query":[{"disabled":false,"description":{"content":"(Required) ","type":"text/plain"},"key":"PhoneNumber","value":"<string>"},{"disabled":false,"description":{"content":"(Required) ","type":"text/plain"},"key":"DeviceId","value":"<string>"},{"disabled":false,"description":{"content":"","type":"text/plain"},"key":"AttemptReference","value":"<string>"}],"variable":[]},"header":[{"key":"Accept","value":"application/json"}],"method":"GET","body":{}},"status":"Not Found","code":404,"header":[{"key":"Content-Type","value":"application/json"}],"body":"{\n  \"errorCode\": \"<string>\",\n  \"message\": \"<string>\",\n  \"detail\": \"<string>\"\n}","cookie":[],"_postman_previewlanguage":"json"}],"event":[],"protocolProfileBehavior":{"disableBodyPruning":true}}]},{"name":"UpdateUserProfile","description":"","item":[{"id":"4e2a2bc2-11c3-4c53-ae7c-f645e8cef4d1","name":"Update User Profile","request":{"name":"Update User Profile","description":{"content":"Updates the partial information of user.","type":"text/plain"},"url":{"path":["api","Auth","UpdateUserProfile"],"host":["{{baseUrl}}"],"query":[],"variable":[]},"header":[{"key":"Content-Type","value":"application/json"},{"key":"Accept","value":"application/json"}],"method":"PATCH","body":{"mode":"raw","raw":"{\n  \"userId\": \"<string>\",\n  \"name\": \"<string>\",\n  \"surname\": \"<string>\",\n  \"birthday\": \"<string>\",\n  \"email\": \"<string>\",\n  \"zipCode\": \"<string>\",\n  \"secondLastName\": \"<string>\",\n  \"gender\": \"M\",\n  \"attemptReference\": \"<string>\",\n  \"deviceId\": \"<string>\"\n}","options":{"raw":{"headerFamily":"json","language":"json"}}},"auth":null},"response":[{"id":"76fc6c77-9a7d-4eb7-98b5-f550917b4721","name":"The information is updated correctly","originalRequest":{"url":{"path":["api","Auth","UpdateUserProfile"],"host":["{{baseUrl}}"],"query":[],"variable":[]},"header":[{"key":"Content-Type","value":"application/json"},{"key":"Accept","value":"application/json"}],"method":"PATCH","body":{"mode":"raw","raw":"{\n  \"userId\": \"<string>\",\n  \"name\": \"<string>\",\n  \"surname\": \"<string>\",\n  \"birthday\": \"<string>\",\n  \"email\": \"<string>\",\n  \"zipCode\": \"<string>\",\n  \"secondLastName\": \"<string>\",\n  \"gender\": \"M\",\n  \"attemptReference\": \"<string>\",\n  \"deviceId\": \"<string>\"\n}","options":{"raw":{"headerFamily":"json","language":"json"}}}},"status":"OK","code":200,"header":[{"key":"Content-Type","value":"application/json"}],"body":"{\n  \"birthday\": \"<string>\",\n  \"emailVerified\": \"<boolean>\",\n  \"firstName\": \"<string>\",\n  \"lastName\": \"<string>\",\n  \"loyaltyId\": \"<string>\",\n  \"phoneNumber\": \"<string>\",\n  \"zipCode\": \"<string>\",\n  \"email\": \"<string>\",\n  \"userName\": \"<string>\",\n  \"secondLastName\": \"<string>\",\n  \"gender\": \"W\"\n}","cookie":[],"_postman_previewlanguage":"json"},{"id":"e3f3a921-ea3e-467f-bda0-e4d6535726b5","name":"- The information is wrong (SPCI-400): the email provided is not valid.","originalRequest":{"url":{"path":["api","Auth","UpdateUserProfile"],"host":["{{baseUrl}}"],"query":[],"variable":[]},"header":[{"key":"Content-Type","value":"application/json"},{"key":"Accept","value":"application/json"}],"method":"PATCH","body":{"mode":"raw","raw":"{\n  \"userId\": \"<string>\",\n  \"name\": \"<string>\",\n  \"surname\": \"<string>\",\n  \"birthday\": \"<string>\",\n  \"email\": \"<string>\",\n  \"zipCode\": \"<string>\",\n  \"secondLastName\": \"<string>\",\n  \"gender\": \"M\",\n  \"attemptReference\": \"<string>\",\n  \"deviceId\": \"<string>\"\n}","options":{"raw":{"headerFamily":"json","language":"json"}}}},"status":"Bad Request","code":400,"header":[{"key":"Content-Type","value":"application/json"}],"body":"{\n  \"errorCode\": \"<string>\",\n  \"message\": \"<string>\",\n  \"detail\": \"<string>\"\n}","cookie":[],"_postman_previewlanguage":"json"},{"id":"f158629c-da67-4a48-9dea-1af128e7583f","name":"- Invalid token (SPCI-401-7): the given token is not valid.\n- Invalid token (SPCI-401-8): the scope header is invalid.\n- Nethone request a review (SPNE-401): review the user.\n- Nethone refuse the request (SPNE-402): user refused.","originalRequest":{"url":{"path":["api","Auth","UpdateUserProfile"],"host":["{{baseUrl}}"],"query":[],"variable":[]},"header":[{"key":"Content-Type","value":"application/json"},{"key":"Accept","value":"application/json"}],"method":"PATCH","body":{"mode":"raw","raw":"{\n  \"userId\": \"<string>\",\n  \"name\": \"<string>\",\n  \"surname\": \"<string>\",\n  \"birthday\": \"<string>\",\n  \"email\": \"<string>\",\n  \"zipCode\": \"<string>\",\n  \"secondLastName\": \"<string>\",\n  \"gender\": \"M\",\n  \"attemptReference\": \"<string>\",\n  \"deviceId\": \"<string>\"\n}","options":{"raw":{"headerFamily":"json","language":"json"}}}},"status":"Unauthorized","code":401,"header":[{"key":"Content-Type","value":"application/json"}],"body":"{\n  \"errorCode\": \"<string>\",\n  \"message\": \"<string>\",\n  \"detail\": \"<string>\"\n}","cookie":[],"_postman_previewlanguage":"json"},{"id":"d03dcaae-2fe0-4407-a50f-ccd429fc8073","name":"- The email has been used. (SPCI-409-2): old email.","originalRequest":{"url":{"path":["api","Auth","UpdateUserProfile"],"host":["{{baseUrl}}"],"query":[],"variable":[]},"header":[{"key":"Content-Type","value":"application/json"},{"key":"Accept","value":"application/json"}],"method":"PATCH","body":{"mode":"raw","raw":"{\n  \"userId\": \"<string>\",\n  \"name\": \"<string>\",\n  \"surname\": \"<string>\",\n  \"birthday\": \"<string>\",\n  \"email\": \"<string>\",\n  \"zipCode\": \"<string>\",\n  \"secondLastName\": \"<string>\",\n  \"gender\": \"M\",\n  \"attemptReference\": \"<string>\",\n  \"deviceId\": \"<string>\"\n}","options":{"raw":{"headerFamily":"json","language":"json"}}}},"status":"Conflict","code":409,"header":[{"key":"Content-Type","value":"application/json"}],"body":"{\n  \"errorCode\": \"<string>\",\n  \"message\": \"<string>\",\n  \"detail\": \"<string>\"\n}","cookie":[],"_postman_previewlanguage":"json"},{"id":"dcd7af84-30e6-4df3-9489-134807d14f79","name":"- Loyalty User was not able to create (SPCI-500): if the user not exists in Loyalty.\n- Unhandled error, is necesary validate the log.","originalRequest":{"url":{"path":["api","Auth","UpdateUserProfile"],"host":["{{baseUrl}}"],"query":[],"variable":[]},"header":[{"key":"Content-Type","value":"application/json"},{"key":"Accept","value":"application/json"}],"method":"PATCH","body":{"mode":"raw","raw":"{\n  \"userId\": \"<string>\",\n  \"name\": \"<string>\",\n  \"surname\": \"<string>\",\n  \"birthday\": \"<string>\",\n  \"email\": \"<string>\",\n  \"zipCode\": \"<string>\",\n  \"secondLastName\": \"<string>\",\n  \"gender\": \"M\",\n  \"attemptReference\": \"<string>\",\n  \"deviceId\": \"<string>\"\n}","options":{"raw":{"headerFamily":"json","language":"json"}}}},"status":"Internal Server Error","code":500,"header":[{"key":"Content-Type","value":"application/json"}],"body":"{\n  \"errorCode\": \"<string>\",\n  \"message\": \"<string>\",\n  \"detail\": \"<string>\"\n}","cookie":[],"_postman_previewlanguage":"json"}],"event":[],"protocolProfileBehavior":{"disableBodyPruning":true}}]},{"name":"TokenValidator","description":"","item":[{"name":"TokenValidator","description":"","item":[{"id":"570c7c46-e7b3-4d3d-8f1e-6b14aad63765","name":"Token Validator","request":{"name":"Token Validator","description":{"content":"validates that the token sent is correct","type":"text/plain"},"url":{"path":["api","Auth","TokenValidator","TokenValidator"],"host":["{{baseUrl}}"],"query":[],"variable":[]},"method":"GET","body":{},"auth":null},"response":[{"id":"80368ad5-c718-45db-a5d8-2a009977f5d3","name":"Success","originalRequest":{"url":{"path":["api","Auth","TokenValidator","TokenValidator"],"host":["{{baseUrl}}"],"query":[],"variable":[]},"method":"GET","body":{}},"status":"OK","code":200,"header":[],"cookie":[],"_postman_previewlanguage":"text"}],"event":[],"protocolProfileBehavior":{"disableBodyPruning":true}}]}]},{"name":"Signup","description":"","item":[{"id":"93ece9bf-fb0a-4f49-9619-8fe7f38433b7","name":"Creates a user if meets the validations.","request":{"name":"Creates a user if meets the validations.","description":{},"url":{"path":["api","Auth","Signup"],"host":["{{baseUrl}}"],"query":[],"variable":[]},"header":[{"key":"Content-Type","value":"application/json"},{"key":"Accept","value":"application/json"}],"method":"POST","body":{"mode":"raw","raw":"{\n  \"birthday\": \"<string>\",\n  \"deviceId\": \"<string>\",\n  \"name\": \"<string>\",\n  \"password\": \"<string>\",\n  \"phoneNumber\": \"<string>\",\n  \"surname\": \"<string>\",\n  \"email\": \"<email>\",\n  \"attemptReference\": \"<string>\"\n}","options":{"raw":{"headerFamily":"json","language":"json"}}},"auth":null},"response":[{"id":"1ebc270c-1d3f-4a37-a9a5-c63f5603a755","name":"Returns access token information.","originalRequest":{"url":{"path":["api","Auth","Signup"],"host":["{{baseUrl}}"],"query":[],"variable":[]},"header":[{"key":"Content-Type","value":"application/json"},{"key":"Accept","value":"application/json"}],"method":"POST","body":{"mode":"raw","raw":"{\n  \"birthday\": \"<string>\",\n  \"deviceId\": \"<string>\",\n  \"name\": \"<string>\",\n  \"password\": \"<string>\",\n  \"phoneNumber\": \"<string>\",\n  \"surname\": \"<string>\",\n  \"email\": \"<email>\",\n  \"attemptReference\": \"<string>\"\n}","options":{"raw":{"headerFamily":"json","language":"json"}}}},"status":"OK","code":200,"header":[{"key":"Content-Type","value":"application/json"}],"body":"{\n  \"accessToken\": \"<string>\",\n  \"expiresIn\": \"<integer>\",\n  \"idToken\": \"<string>\",\n  \"refreshToken\": \"<string>\",\n  \"tokenType\": \"<string>\"\n}","cookie":[],"_postman_previewlanguage":"json"},{"id":"ba4b334b-740c-4a28-9a5c-f5c1a788114f","name":"Unhandled error, validate the error log.","originalRequest":{"url":{"path":["api","Auth","Signup"],"host":["{{baseUrl}}"],"query":[],"variable":[]},"header":[{"key":"Content-Type","value":"application/json"}],"method":"POST","body":{"mode":"raw","raw":"{\n  \"birthday\": \"<string>\",\n  \"deviceId\": \"<string>\",\n  \"name\": \"<string>\",\n  \"password\": \"<string>\",\n  \"phoneNumber\": \"<string>\",\n  \"surname\": \"<string>\",\n  \"email\": \"<email>\",\n  \"attemptReference\": \"<string>\"\n}","options":{"raw":{"headerFamily":"json","language":"json"}}}},"status":"Internal Server Error","code":500,"header":[],"cookie":[],"_postman_previewlanguage":"text"}],"event":[],"protocolProfileBehavior":{"disableBodyPruning":true}}]},{"name":"RevokeRefreshToken","description":"","item":[{"id":"e905b3cf-f899-45cc-8fd4-2468ddd442f2","name":"Revoke Refresh Token","request":{"name":"Revoke Refresh Token","description":{"content":"Some endpoint description goes here.","type":"text/plain"},"url":{"path":["api","Auth","RevokeRefreshToken"],"host":["{{baseUrl}}"],"query":[],"variable":[]},"header":[{"key":"Content-Type","value":"application/json"},{"key":"Accept","value":"application/json"}],"method":"POST","body":{"mode":"raw","raw":"{\n  \"refreshToken\": \"<string>\"\n}","options":{"raw":{"headerFamily":"json","language":"json"}}},"auth":null},"response":[{"id":"7ec19ace-38b3-4fd6-b389-ecb80edeea67","name":"Response","originalRequest":{"url":{"path":["api","Auth","RevokeRefreshToken"],"host":["{{baseUrl}}"],"query":[],"variable":[]},"header":[{"key":"Content-Type","value":"application/json"},{"key":"Accept","value":"application/json"}],"method":"POST","body":{"mode":"raw","raw":"{\n  \"refreshToken\": \"<string>\"\n}","options":{"raw":{"headerFamily":"json","language":"json"}}}},"status":"OK","code":200,"header":[{"key":"Content-Type","value":"application/json"}],"body":"{\n  \"refreshToken\": \"<string>\"\n}","cookie":[],"_postman_previewlanguage":"json"},{"id":"d9a4a4f9-7045-4783-be66-9f53049c26ba","name":"Unhandled error, validate the error log.","originalRequest":{"url":{"path":["api","Auth","RevokeRefreshToken"],"host":["{{baseUrl}}"],"query":[],"variable":[]},"header":[{"key":"Content-Type","value":"application/json"},{"key":"Accept","value":"application/json"}],"method":"POST","body":{"mode":"raw","raw":"{\n  \"refreshToken\": \"<string>\"\n}","options":{"raw":{"headerFamily":"json","language":"json"}}}},"status":"Internal Server Error","code":500,"header":[{"key":"Content-Type","value":"application/json"}],"body":"{\n  \"httpCode\": 302,\n  \"errorCode\": \"<string>\",\n  \"type\": \"<string>\"\n}","cookie":[],"_postman_previewlanguage":"json"}],"event":[],"protocolProfileBehavior":{"disableBodyPruning":true}}]},{"name":"RefreshToken","description":"","item":[{"id":"7451d3d5-5a67-4a9e-a58f-e73e20535617","name":"Generates a new refresh token.","request":{"name":"Generates a new refresh token.","description":{},"url":{"path":["api","Auth","RefreshToken"],"host":["{{baseUrl}}"],"query":[],"variable":[]},"header":[{"key":"Content-Type","value":"application/json"},{"key":"Accept","value":"application/json"}],"method":"POST","body":{"mode":"raw","raw":"{\n  \"refreshToken\": \"<string>\"\n}","options":{"raw":{"headerFamily":"json","language":"json"}}},"auth":null},"response":[{"id":"d95c0c1d-4cff-41b7-b5a6-76e7df513665","name":"Returns a status of the user.","originalRequest":{"url":{"path":["api","Auth","RefreshToken"],"host":["{{baseUrl}}"],"query":[],"variable":[]},"header":[{"key":"Content-Type","value":"application/json"},{"key":"Accept","value":"application/json"}],"method":"POST","body":{"mode":"raw","raw":"{\n  \"refreshToken\": \"<string>\"\n}","options":{"raw":{"headerFamily":"json","language":"json"}}}},"status":"OK","code":200,"header":[{"key":"Content-Type","value":"application/json"}],"body":"{\n  \"accessToken\": \"<string>\",\n  \"expiresIn\": \"<integer>\",\n  \"idToken\": \"<string>\",\n  \"refreshToken\": \"<string>\",\n  \"tokenType\": \"<string>\"\n}","cookie":[],"_postman_previewlanguage":"json"},{"id":"fb1daa5e-a9a6-43b1-b3a8-3a5ad94472bd","name":"Unhandled error, validate the error log.","originalRequest":{"url":{"path":["api","Auth","RefreshToken"],"host":["{{baseUrl}}"],"query":[],"variable":[]},"header":[{"key":"Content-Type","value":"application/json"}],"method":"POST","body":{"mode":"raw","raw":"{\n  \"refreshToken\": \"<string>\"\n}","options":{"raw":{"headerFamily":"json","language":"json"}}}},"status":"Internal Server Error","code":500,"header":[],"cookie":[],"_postman_previewlanguage":"text"}],"event":[],"protocolProfileBehavior":{"disableBodyPruning":true}}]},{"name":"RecoveryUserPassword","description":"","item":[{"id":"b48430ac-0406-4ade-afe0-0cf38e5e8a59","name":"Recovery User Password","request":{"name":"Recovery User Password","description":{"content":"Recovery an user's password, based on the requested data.","type":"text/plain"},"url":{"path":["api","Auth","RecoveryUserPassword"],"host":["{{baseUrl}}"],"query":[],"variable":[]},"header":[{"key":"Content-Type","value":"application/json"},{"key":"Accept","value":"application/json"}],"method":"POST","body":{"mode":"raw","raw":"{\n  \"newPassword\": \"<string>\",\n  \"phoneNumber\": \"<string>\",\n  \"deviceId\": \"<string>\",\n  \"attemptReference\": \"<string>\"\n}","options":{"raw":{"headerFamily":"json","language":"json"}}},"auth":null},"response":[{"id":"4340b543-c358-49ba-9f93-013340518536","name":"The password was recovered successfully.","originalRequest":{"url":{"path":["api","Auth","RecoveryUserPassword"],"host":["{{baseUrl}}"],"query":[],"variable":[]},"header":[{"key":"Content-Type","value":"application/json"},{"key":"Accept","value":"application/json"}],"method":"POST","body":{"mode":"raw","raw":"{\n  \"newPassword\": \"<string>\",\n  \"phoneNumber\": \"<string>\",\n  \"deviceId\": \"<string>\",\n  \"attemptReference\": \"<string>\"\n}","options":{"raw":{"headerFamily":"json","language":"json"}}}},"status":"OK","code":200,"header":[{"key":"Content-Type","value":"application/json"}],"body":"{\n  \"birthday\": \"<string>\",\n  \"emailVerified\": \"<boolean>\",\n  \"firstName\": \"<string>\",\n  \"lastName\": \"<string>\",\n  \"loyaltyId\": \"<string>\",\n  \"phoneNumber\": \"<string>\",\n  \"zipCode\": \"<string>\",\n  \"email\": \"<string>\",\n  \"userName\": \"<string>\",\n  \"secondLastName\": \"<string>\",\n  \"gender\": \"W\"\n}","cookie":[],"_postman_previewlanguage":"json"},{"id":"df33367f-bc3e-4427-86fd-d3daab2158ef","name":"- Invalid token (SPCI-401-7): the given token is not valid.\n- Invalid token (SPCI-401-8): the scope header is invalid.","originalRequest":{"url":{"path":["api","Auth","RecoveryUserPassword"],"host":["{{baseUrl}}"],"query":[],"variable":[]},"header":[{"key":"Content-Type","value":"application/json"},{"key":"Accept","value":"application/json"}],"method":"POST","body":{"mode":"raw","raw":"{\n  \"newPassword\": \"<string>\",\n  \"phoneNumber\": \"<string>\",\n  \"deviceId\": \"<string>\",\n  \"attemptReference\": \"<string>\"\n}","options":{"raw":{"headerFamily":"json","language":"json"}}}},"status":"Unauthorized","code":401,"header":[{"key":"Content-Type","value":"application/json"}],"body":"{\n  \"errorCode\": \"<string>\",\n  \"message\": \"<string>\",\n  \"detail\": \"<string>\"\n}","cookie":[],"_postman_previewlanguage":"json"},{"id":"ff8ecac3-3736-48db-ab27-477464321d2d","name":"- ChangeUserPassword User Not Found in Auth0 (SPCI-500): error. \n- Invalid grant to recover password (SPCI-500): error. \n- RecoveryUserPassword User Not Found in Auth0. (SPCI-500): error.\n- Unhandled error, is necesary validate the log.\n","originalRequest":{"url":{"path":["api","Auth","RecoveryUserPassword"],"host":["{{baseUrl}}"],"query":[],"variable":[]},"header":[{"key":"Content-Type","value":"application/json"},{"key":"Accept","value":"application/json"}],"method":"POST","body":{"mode":"raw","raw":"{\n  \"newPassword\": \"<string>\",\n  \"phoneNumber\": \"<string>\",\n  \"deviceId\": \"<string>\",\n  \"attemptReference\": \"<string>\"\n}","options":{"raw":{"headerFamily":"json","language":"json"}}}},"status":"Internal Server Error","code":500,"header":[{"key":"Content-Type","value":"application/json"}],"body":"{\n  \"errorCode\": \"<string>\",\n  \"message\": \"<string>\",\n  \"detail\": \"<string>\"\n}","cookie":[],"_postman_previewlanguage":"json"}],"event":[],"protocolProfileBehavior":{"disableBodyPruning":true}}]},{"name":"Login","description":"","item":[{"id":"105e3bec-e23e-45c2-8140-ff6f95505def","name":"Validates if the user has permissions to log in.","request":{"name":"Validates if the user has permissions to log in.","description":{},"url":{"path":["api","Auth","Login"],"host":["{{baseUrl}}"],"query":[],"variable":[]},"header":[{"key":"Content-Type","value":"application/json"},{"key":"Accept","value":"application/json"}],"method":"POST","body":{"mode":"raw","raw":"{\n  \"deviceId\": \"<string>\",\n  \"password\": \"<string>\",\n  \"username\": \"<string>\",\n  \"attemptReference\": \"<string>\"\n}","options":{"raw":{"headerFamily":"json","language":"json"}}},"auth":null},"response":[{"id":"b0016a45-0ccb-4813-a70a-9ac171f308e1","name":"Returns access token information.","originalRequest":{"url":{"path":["api","Auth","Login"],"host":["{{baseUrl}}"],"query":[],"variable":[]},"header":[{"key":"Content-Type","value":"application/json"},{"key":"Accept","value":"application/json"}],"method":"POST","body":{"mode":"raw","raw":"{\n  \"deviceId\": \"<string>\",\n  \"password\": \"<string>\",\n  \"username\": \"<string>\",\n  \"attemptReference\": \"<string>\"\n}","options":{"raw":{"headerFamily":"json","language":"json"}}}},"status":"OK","code":200,"header":[{"key":"Content-Type","value":"application/json"}],"body":"{\n  \"accessToken\": \"<string>\",\n  \"expiresIn\": \"<integer>\",\n  \"idToken\": \"<string>\",\n  \"refreshToken\": \"<string>\",\n  \"tokenType\": \"<string>\"\n}","cookie":[],"_postman_previewlanguage":"json"},{"id":"96c1d954-f082-4822-9012-a5243c4b7189","name":"Unauthorized","originalRequest":{"url":{"path":["api","Auth","Login"],"host":["{{baseUrl}}"],"query":[],"variable":[]},"header":[{"key":"Content-Type","value":"application/json"},{"key":"Accept","value":"application/json"}],"method":"POST","body":{"mode":"raw","raw":"{\n  \"deviceId\": \"<string>\",\n  \"password\": \"<string>\",\n  \"username\": \"<string>\",\n  \"attemptReference\": \"<string>\"\n}","options":{"raw":{"headerFamily":"json","language":"json"}}}},"status":"Unauthorized","code":401,"header":[{"key":"Content-Type","value":"application/json"}],"body":"{\n  \"type\": \"<string>\",\n  \"title\": \"<string>\",\n  \"status\": \"<integer>\",\n  \"detail\": \"<string>\",\n  \"instance\": \"<string>\",\n  \"dolore5\": {}\n}","cookie":[],"_postman_previewlanguage":"json"},{"id":"c9422bc8-9e1a-4724-83fe-7a75f27c4c57","name":"Client Error","originalRequest":{"url":{"path":["api","Auth","Login"],"host":["{{baseUrl}}"],"query":[],"variable":[]},"header":[{"key":"Content-Type","value":"application/json"},{"key":"Accept","value":"application/json"}],"method":"POST","body":{"mode":"raw","raw":"{\n  \"deviceId\": \"<string>\",\n  \"password\": \"<string>\",\n  \"username\": \"<string>\",\n  \"attemptReference\": \"<string>\"\n}","options":{"raw":{"headerFamily":"json","language":"json"}}}},"status":"Payment Required","code":402,"header":[{"key":"Content-Type","value":"application/json"}],"body":"{\n  \"type\": \"<string>\",\n  \"title\": \"<string>\",\n  \"status\": \"<integer>\",\n  \"detail\": \"<string>\",\n  \"instance\": \"<string>\",\n  \"dolore5\": {}\n}","cookie":[],"_postman_previewlanguage":"json"},{"id":"73e4e511-f043-467f-acbc-40a17ca9cb1b","name":"Not Found","originalRequest":{"url":{"path":["api","Auth","Login"],"host":["{{baseUrl}}"],"query":[],"variable":[]},"header":[{"key":"Content-Type","value":"application/json"},{"key":"Accept","value":"application/json"}],"method":"POST","body":{"mode":"raw","raw":"{\n  \"deviceId\": \"<string>\",\n  \"password\": \"<string>\",\n  \"username\": \"<string>\",\n  \"attemptReference\": \"<string>\"\n}","options":{"raw":{"headerFamily":"json","language":"json"}}}},"status":"Not Found","code":404,"header":[{"key":"Content-Type","value":"application/json"}],"body":"{\n  \"type\": \"<string>\",\n  \"title\": \"<string>\",\n  \"status\": \"<integer>\",\n  \"detail\": \"<string>\",\n  \"instance\": \"<string>\",\n  \"dolore5\": {}\n}","cookie":[],"_postman_previewlanguage":"json"},{"id":"5ccd9d15-303d-42ee-9ff3-bfae4758ae87","name":"Unhandled error, validate the error log.","originalRequest":{"url":{"path":["api","Auth","Login"],"host":["{{baseUrl}}"],"query":[],"variable":[]},"header":[{"key":"Content-Type","value":"application/json"}],"method":"POST","body":{"mode":"raw","raw":"{\n  \"deviceId\": \"<string>\",\n  \"password\": \"<string>\",\n  \"username\": \"<string>\",\n  \"attemptReference\": \"<string>\"\n}","options":{"raw":{"headerFamily":"json","language":"json"}}}},"status":"Internal Server Error","code":500,"header":[],"cookie":[],"_postman_previewlanguage":"text"}],"event":[],"protocolProfileBehavior":{"disableBodyPruning":true}}]},{"name":"GetUserProfile","description":"","item":[{"id":"0a743c20-9ab7-4c56-9eb3-fdd278aa3543","name":"Get User Profile","request":{"name":"Get User Profile","description":{"content":"Some endpoint description goes here.","type":"text/plain"},"url":{"path":["api","Auth","GetUserProfile"],"host":["{{baseUrl}}"],"query":[{"disabled":false,"description":{"content":"","type":"text/plain"},"key":"UserId","value":"<string>"},{"disabled":false,"description":{"content":"","type":"text/plain"},"key":"PhoneNumber","value":"<string>"}],"variable":[]},"header":[{"key":"Accept","value":"application/json"}],"method":"GET","body":{},"auth":null},"response":[{"id":"cc9f9bb6-2158-4621-bd68-73c4b807a0e6","name":"Response","originalRequest":{"url":{"path":["api","Auth","GetUserProfile"],"host":["{{baseUrl}}"],"query":[{"disabled":false,"description":{"content":"","type":"text/plain"},"key":"UserId","value":"<string>"},{"disabled":false,"description":{"content":"","type":"text/plain"},"key":"PhoneNumber","value":"<string>"}],"variable":[]},"header":[{"key":"Accept","value":"application/json"}],"method":"GET","body":{}},"status":"OK","code":200,"header":[{"key":"Content-Type","value":"application/json"}],"body":"{\n  \"birthday\": \"<string>\",\n  \"emailVerified\": \"<boolean>\",\n  \"firstName\": \"<string>\",\n  \"lastName\": \"<string>\",\n  \"loyaltyId\": \"<string>\",\n  \"phoneNumber\": \"<string>\",\n  \"zipCode\": \"<string>\",\n  \"email\": \"<string>\",\n  \"userName\": \"<string>\"\n}","cookie":[],"_postman_previewlanguage":"json"},{"id":"c97f352c-e972-4327-80b2-998750ad8a95","name":"Unhandled error, validate the error log.","originalRequest":{"url":{"path":["api","Auth","GetUserProfile"],"host":["{{baseUrl}}"],"query":[{"disabled":false,"description":{"content":"","type":"text/plain"},"key":"UserId","value":"<string>"},{"disabled":false,"description":{"content":"","type":"text/plain"},"key":"PhoneNumber","value":"<string>"}],"variable":[]},"header":[{"key":"Accept","value":"application/json"}],"method":"GET","body":{}},"status":"Internal Server Error","code":500,"header":[{"key":"Content-Type","value":"application/json"}],"body":"{\n  \"httpCode\": 302,\n  \"errorCode\": \"<string>\",\n  \"type\": \"<string>\"\n}","cookie":[],"_postman_previewlanguage":"json"}],"event":[],"protocolProfileBehavior":{"disableBodyPruning":true}}]},{"name":"GetTransversalUserData","description":"","item":[{"id":"acb8f309-ee10-4abb-b686-b8603167678d","name":"Get Transversal User Data","request":{"name":"Get Transversal User Data","description":{"content":"Some endpoint description goes here.","type":"text/plain"},"url":{"path":["api","Auth","GetTransversalUserData"],"host":["{{baseUrl}}"],"query":[{"disabled":false,"description":{"content":"(Required) ","type":"text/plain"},"key":"PhoneNumber","value":"<string>"},{"disabled":false,"description":{"content":"(Required) ","type":"text/plain"},"key":"DeviceId","value":"<string>"}],"variable":[]},"header":[{"key":"Accept","value":"application/json"}],"method":"GET","body":{},"auth":null},"response":[{"id":"237d532f-1ccb-4391-bf1a-889695807a17","name":"Response","originalRequest":{"url":{"path":["api","Auth","GetTransversalUserData"],"host":["{{baseUrl}}"],"query":[{"disabled":false,"description":{"content":"(Required) ","type":"text/plain"},"key":"PhoneNumber","value":"<string>"},{"disabled":false,"description":{"content":"(Required) ","type":"text/plain"},"key":"DeviceId","value":"<string>"}],"variable":[]},"header":[{"key":"Accept","value":"application/json"}],"method":"GET","body":{}},"status":"OK","code":200,"header":[{"key":"Content-Type","value":"application/json"}],"body":"{\n  \"firstName\": \"<string>\",\n  \"lastName\": \"<string>\",\n  \"email\": \"<string>\"\n}","cookie":[],"_postman_previewlanguage":"json"},{"id":"91e8f671-9164-4f10-a895-c4bde80936c8","name":"Unhandled error, validate the error log.","originalRequest":{"url":{"path":["api","Auth","GetTransversalUserData"],"host":["{{baseUrl}}"],"query":[{"disabled":false,"description":{"content":"(Required) ","type":"text/plain"},"key":"PhoneNumber","value":"<string>"},{"disabled":false,"description":{"content":"(Required) ","type":"text/plain"},"key":"DeviceId","value":"<string>"}],"variable":[]},"header":[{"key":"Accept","value":"application/json"}],"method":"GET","body":{}},"status":"Internal Server Error","code":500,"header":[{"key":"Content-Type","value":"application/json"}],"body":"{\n  \"httpCode\": 302,\n  \"errorCode\": \"<string>\",\n  \"type\": \"<string>\"\n}","cookie":[],"_postman_previewlanguage":"json"}],"event":[],"protocolProfileBehavior":{"disableBodyPruning":true}}]},{"name":"ChangeUserProperty","description":"","item":[{"id":"9d77d4f7-73b8-425d-b602-8302a2ed9f8f","name":"Change User Property","request":{"name":"Change User Property","description":{"content":"This endpoint will change the property of the user.","type":"text/plain"},"url":{"path":["api","Auth","ChangeUserProperty"],"host":["{{baseUrl}}"],"query":[],"variable":[]},"header":[{"key":"Content-Type","value":"application/json"},{"key":"Accept","value":"application/json"}],"method":"POST","body":{"mode":"raw","raw":"{\n  \"userId\": \"<string>\",\n  \"email\": \"<string>\",\n  \"phoneNumber\": \"<string>\"\n}","options":{"raw":{"headerFamily":"json","language":"json"}}},"auth":null},"response":[{"id":"cbe04fa9-5964-4cfb-8a9c-fa12c69ad991","name":"Returns a 200 if the user property change.","originalRequest":{"url":{"path":["api","Auth","ChangeUserProperty"],"host":["{{baseUrl}}"],"query":[],"variable":[]},"header":[{"key":"Content-Type","value":"application/json"}],"method":"POST","body":{"mode":"raw","raw":"{\n  \"userId\": \"<string>\",\n  \"email\": \"<string>\",\n  \"phoneNumber\": \"<string>\"\n}","options":{"raw":{"headerFamily":"json","language":"json"}}}},"status":"OK","code":200,"header":[],"cookie":[],"_postman_previewlanguage":"text"},{"id":"27cd68ff-41a4-433b-82ca-f35392762192","name":"SPCI-404: User not found","originalRequest":{"url":{"path":["api","Auth","ChangeUserProperty"],"host":["{{baseUrl}}"],"query":[],"variable":[]},"header":[{"key":"Content-Type","value":"application/json"},{"key":"Accept","value":"application/json"}],"method":"POST","body":{"mode":"raw","raw":"{\n  \"userId\": \"<string>\",\n  \"email\": \"<string>\",\n  \"phoneNumber\": \"<string>\"\n}","options":{"raw":{"headerFamily":"json","language":"json"}}}},"status":"Not Found","code":404,"header":[{"key":"Content-Type","value":"application/json"}],"body":"{\n  \"errorCode\": \"<string>\",\n  \"message\": \"<string>\",\n  \"detail\": \"<string>\"\n}","cookie":[],"_postman_previewlanguage":"json"}],"event":[],"protocolProfileBehavior":{"disableBodyPruning":true}}]},{"name":"ChangeUserPassword","description":"","item":[{"id":"3e47b447-1639-45df-9cc2-3f1649e36f8c","name":"Change User Password","request":{"name":"Change User Password","description":{"content":"This endpoint will change the password of the user.","type":"text/plain"},"url":{"path":["api","Auth","ChangeUserPassword"],"host":["{{baseUrl}}"],"query":[],"variable":[]},"header":[{"key":"Content-Type","value":"application/json"},{"key":"Accept","value":"application/json"}],"method":"POST","body":{"mode":"raw","raw":"{\n  \"newPassword\": \"<string>\",\n  \"userId\": \"<string>\",\n  \"currentPassword\": \"<string>\"\n}","options":{"raw":{"headerFamily":"json","language":"json"}}},"auth":null},"response":[{"id":"478615c3-87ba-4a6f-91dd-75f253571f10","name":"Response","originalRequest":{"url":{"path":["api","Auth","ChangeUserPassword"],"host":["{{baseUrl}}"],"query":[],"variable":[]},"header":[{"key":"Content-Type","value":"application/json"},{"key":"Accept","value":"application/json"}],"method":"POST","body":{"mode":"raw","raw":"{\n  \"newPassword\": \"<string>\",\n  \"userId\": \"<string>\",\n  \"currentPassword\": \"<string>\"\n}","options":{"raw":{"headerFamily":"json","language":"json"}}}},"status":"OK","code":200,"header":[{"key":"Content-Type","value":"application/json"}],"body":"{\n  \"birthday\": \"<string>\",\n  \"emailVerified\": \"<boolean>\",\n  \"firstName\": \"<string>\",\n  \"lastName\": \"<string>\",\n  \"loyaltyId\": \"<string>\",\n  \"phoneNumber\": \"<string>\",\n  \"zipCode\": \"<string>\",\n  \"email\": \"<string>\",\n  \"userName\": \"<string>\"\n}","cookie":[],"_postman_previewlanguage":"json"},{"id":"67818e9b-8b2f-43c2-bf3d-e0eadc3f6c30","name":"SPCI-404: User not found","originalRequest":{"url":{"path":["api","Auth","ChangeUserPassword"],"host":["{{baseUrl}}"],"query":[],"variable":[]},"header":[{"key":"Content-Type","value":"application/json"},{"key":"Accept","value":"application/json"}],"method":"POST","body":{"mode":"raw","raw":"{\n  \"newPassword\": \"<string>\",\n  \"userId\": \"<string>\",\n  \"currentPassword\": \"<string>\"\n}","options":{"raw":{"headerFamily":"json","language":"json"}}}},"status":"Not Found","code":404,"header":[{"key":"Content-Type","value":"application/json"}],"body":"{\n  \"errorCode\": \"<string>\",\n  \"message\": \"<string>\",\n  \"detail\": \"<string>\"\n}","cookie":[],"_postman_previewlanguage":"json"}],"event":[],"protocolProfileBehavior":{"disableBodyPruning":true}}]},{"name":"CancelUserAccount","description":"","item":[{"name":"CancelUserAccount","description":"","item":[{"id":"183bc255-864f-4b8b-a256-8017e2af23ac","name":"Cancel User Account","request":{"name":"Cancel User Account","description":{"content":"Recovery an user's password, based on the requested data.","type":"text/plain"},"url":{"path":["api","Auth","CancelUserAccount","CancelUserAccount"],"host":["{{baseUrl}}"],"query":[],"variable":[]},"header":[{"key":"Content-Type","value":"application/json"},{"key":"Accept","value":"application/json"}],"method":"POST","body":{"mode":"raw","raw":"{\n  \"cancellationReason\": \"<string>\",\n  \"password\": \"<string>\",\n  \"userId\": \"<string>\"\n}","options":{"raw":{"headerFamily":"json","language":"json"}}},"auth":null},"response":[{"id":"06918689-40fd-4a40-8f84-f3a39556b9d3","name":"The account is close correctly.","originalRequest":{"url":{"path":["api","Auth","CancelUserAccount","CancelUserAccount"],"host":["{{baseUrl}}"],"query":[],"variable":[]},"header":[{"key":"Content-Type","value":"application/json"},{"key":"Accept","value":"application/json"}],"method":"POST","body":{"mode":"raw","raw":"{\n  \"cancellationReason\": \"<string>\",\n  \"password\": \"<string>\",\n  \"userId\": \"<string>\"\n}","options":{"raw":{"headerFamily":"json","language":"json"}}}},"status":"OK","code":200,"header":[{"key":"Content-Type","value":"application/json"}],"body":"{\n  \"successfulCancellation\": \"<boolean>\"\n}","cookie":[],"_postman_previewlanguage":"json"},{"id":"aa2288ad-4407-45de-bcea-2985d9ecf16c","name":"- The username or password is incorrect (SPCI-401-1): incorrect data (wrong email or password).","originalRequest":{"url":{"path":["api","Auth","CancelUserAccount","CancelUserAccount"],"host":["{{baseUrl}}"],"query":[],"variable":[]},"header":[{"key":"Content-Type","value":"application/json"},{"key":"Accept","value":"application/json"}],"method":"POST","body":{"mode":"raw","raw":"{\n  \"cancellationReason\": \"<string>\",\n  \"password\": \"<string>\",\n  \"userId\": \"<string>\"\n}","options":{"raw":{"headerFamily":"json","language":"json"}}}},"status":"Unauthorized","code":401,"header":[{"key":"Content-Type","value":"application/json"}],"body":"{\n  \"errorCode\": \"<string>\",\n  \"message\": \"<string>\",\n  \"detail\": \"<string>\"\n}","cookie":[],"_postman_previewlanguage":"json"},{"id":"ec5325f4-66f3-4ec1-b8f4-69f6ef12a10a","name":"- CancelUserAccount User Not Found in Auth0 (SPCI-500): error.\n- CancelUserAccount invalid grant.(SPCI-500): error.\n- Generic error from Auth0 Service.(SPCI-500): error.\n- Unhandled error, is necesary validate the log.","originalRequest":{"url":{"path":["api","Auth","CancelUserAccount","CancelUserAccount"],"host":["{{baseUrl}}"],"query":[],"variable":[]},"header":[{"key":"Content-Type","value":"application/json"},{"key":"Accept","value":"application/json"}],"method":"POST","body":{"mode":"raw","raw":"{\n  \"cancellationReason\": \"<string>\",\n  \"password\": \"<string>\",\n  \"userId\": \"<string>\"\n}","options":{"raw":{"headerFamily":"json","language":"json"}}}},"status":"Internal Server Error","code":500,"header":[{"key":"Content-Type","value":"application/json"}],"body":"{\n  \"errorCode\": \"<string>\",\n  \"message\": \"<string>\",\n  \"detail\": \"<string>\"\n}","cookie":[],"_postman_previewlanguage":"json"}],"event":[],"protocolProfileBehavior":{"disableBodyPruning":true}}]}]}]}]}],"event":[],"variable":[{"key":"baseUrl","value":"/"}],"info":{"_postman_id":"fb7ffe25-eb33-4603-af97-6fe26a05c1ec","name":"CIAM Demo Documentation","schema":"https://schema.getpostman.com/json/collection/v2.1.0/collection.json","description":{"content":"# RedocPro\n\nImplementacin del servicio Customer Identity and Access Management (CIAM)  \n <!---![Alt text](image.png)-->\n\n## Endpoints\n\nHasta el momento, se cuentan con los siguientes endpoints:\n- `Login`: \n- `Signup`:\n- `RefreshToken`: \n- `ChangeUserPassword`: \n- `ChangeUserProperty`: \n- `UserValidation`: \n- `RevokeRefreshToken`:\n\nPara descargar la coleccin de Postman puede hacer <a href=\"postman_collection.json\" download>click aqu</a>\n\n\n\nPara descargar las variables de entorno de Postman puede hacer <a href=\"test_environment.json\" download>click aqu</a>\n\n## Ejecucin local\nPara ejecutar de forma local, se pueden seguir los siguientes pasos:\n1. Instalar la versin ms reciente de Visual Studio.\n2. Descargar el `.zip` de la rama `main` del repositorio.\n3. Abrir el proyecto\n4. Agregar en el [`appsettings.Development.json`]\n5. Ahora, puedes hacer click en la ejecutar el proyecto, o bien, en \"Depurar > Iniciar depuracin\".\n\nDonde puedes interactuar con los endpoints de CIAM. Si no se abre la ventana, puedes ingresar a esta por medio del siguiente enlace: [https://localhost:7131/swagger).\n\n## Como contribuir al repositorio\nPara contribuir al repositorio se te deben otorgar permisos de escritura y seguir los siguientes pasos. \n\n1. Asociar un nuevo SSH con tu cuenta de GitHub institucional.\n\n    En esta ocasin, no basta con descargar el `.zip` del repositorio. Debes configurar tu dispositivo para conectar tu cuenta de GitHub mediante SSH, puedes seguir el siguiente [tutorial de GitHub](https://docs.github.com/en/authentication/connecting-to-github-with-ssh/adding-a-new-ssh-key-to-your-github-account) para aadir una SSH a tu cuenta. Adems, debes darle permisos para acceder a `digitaltitransversal`, sigue el siguiente [tutorial](https://docs.github.com/en/enterprise-cloud@latest/authentication/authenticating-with-saml-single-sign-on/authorizing-an-ssh-key-for-use-with-saml-single-sign-on) para dar dichos permisos.\n\n2. Teniendo ya el SSH configurado, debes clonar el repositorio en la carpeta de tu preferencia. Como sugerencia, puedes crear una carpeta `~/Projects` para mantener todos los proyectos en un slo lugar.\n\n    En la terminal, corre el siguiente comando:\n    ```\n    git clone git@github.com:\n    ```\n\n    Debera aparecer una salida parecida a:\n    ```\n    remote: Enumerating objects: 542, done.\n    remote: Counting objects: 100% (314/314), done.\n    remote: Compressing objects: 100% (177/177), done.\n    remote: Total 542 (delta 196), reused 178 (delta 122), pack-reused 228\n    Receiving objects: 100% (542/542), 110.60 KiB | 1.44 MiB/s, done.\n    Resolving deltas: 100% (271/271), done.\n    ```\n\n3. En este punto, se pueden seguir los pasos que se describieron para la ejecucin local.\n\n4. Si se quiere agregar nuevos cambios, debes crear tu propia rama.\n    ```\n    git branch rama-de-ejemplo\n    ```\n\n5. Para empezar a trabajar sobre la rama creada, puedes ejecutar el siguiente comando:\n\n    ```\n    git checkout rama-de-ejemplo\n    ```\n\n    En este punto ya puedes comenzar a hacer tus cambios. Si no haces el `checkout` a tu rama, puede que afectes a otras ramas e interrumpir el trabajo de los dems. Recuerda que no te dejar hacer `push` a `main`. \n\n6. Despus de hacer tus cambios, haz pruebas unitarias e\n\n7. Se checa de manera automtica que se cumpla ciertas reglas de sintaxis. Algunas de estas reglas son necesarias para tener una sintaxis consistente en todo el repositorio. La mayora de las reglas se pueden aplicar de manera automtica corriendo el siguiente comando:\n    ```\n    dotnet format\n    ```\n    En caso de enviar tus cambios y todava tener pendientes de sintaxis, tendrs que checar de forma manual cmo arreglarlo. Te puedes guiar de la [documentacin de StyleCop](https://github.com/DotNetAnalyzers/StyleCopAnalyzers/tree/master/documentation) y pedir ayuda al equipo. Para checar de forma local la sintaxis, puedes correr el siguiente comando:\n\n    ```\n    dotnet format --verify-no-changes --verbosity m --severity warn\n    ```\n\n\n\n# FAQ for developers\n\nPreguntas frecuentes etc..\n\n## Seccin 1\n## Seccin 2\n\n# Clave GPG\n## Requerimientos\n   \n  * El usuario debe tener instalado [Gnupg](https://www.gnupg.org/download) y [Git Bash](https://git-scm.com/downloads) para usuarios con Windows.\n  * El usuario debe tener instalado [Brew](https://brew.sh/index_es) para usuarios con MacBook.\n\n## Generacin con MacBook\n\n1. Abre la Terminal.\n\n2. Verifica si ya tienes instalado GPG en tu Mac escribiendo el siguiente comando y presionando enter:\n```\n    gpg --version  \n```\n   *NOTA: GPG ya est instalado, vers la versin instalada y podrs continuar con el paso 4. Si no lo tienes instalado, continua con el paso 3.*\n\n3. Si no tiene GPG, el Usuario instala GPG con Homebrew.\n```\n    brew install gnupg\n```\n4. El Usuario le indica a GPG que genere una clave GPG.\n    * GPG solicita al Usuario la informacin requerida para generar la clave (nombre, direccin de correo electrnico, contrasea, etc.).\n    * Es muy importante que la logitud de la clave sea de: 4,096\n\n6. El Usuario ingresa la informacin requerida para generar sus clave gpg. \n   * Exportar la clave \n```\n    gpg --full-generate-key\n    gpg --list-secret-keys --keyid-format=long\n```\n   * Copia el ID de la clave que acabas de generar (debera tener el formato4096R/XXXXXXXXXXXXXXXX).\n   * Configura Git para usar tu clave de firma ejecutando los siguientes comandos:\n```\n   git config --global user.signingkey XXXXXXXXXXXXXXXX\n    git config --global commit.gpgsign true\n```\n    \n7. Se obtiene la clave gpg en la terminal para exportarla a Github\n```\n    gpg --armor --export [key_id]\n```\n8. GPG muestra la clave generada al Usuario.\n\n9. La clave generada se guarda dentro de Github en el apartado de [GPG keys](https://github.com/settings/keys)\n\n10. Prueba que puedas firmar tus commits \n    * El siguiente comando mostrara tu configuracin, la cual debe ser parecida a la siguiente:\n    \n```\n    user.signingkey=[Key]\n    gpg.program=gpg2\n    commit.gpgsign=true\n    git commit -S -m [Develop] Comment\n```\n\n11. En caso de no ser exitoso, ejecuta lo siguiente:\n\n```\n    brew install pinentry-mac\n    echo \"pinentry-program $(which pinentry-mac)\" >> ~/.gnupg/gpg-agent.conf\n    killall gpg-agent\n    $ if [ -r ~/.bash_profile ]; then echo 'export GPG_TTY=$(tty)' >> ~/.bash_profile; \\\n\n    else echo 'export GPG_TTY=$(tty)' >> ~/.profile; fi\n    \n    $ if [ -r ~/.zshrc ]; then echo 'export GPG_TTY=$(tty)' >> ~/.zshrc; \\\n\n  else echo 'export GPG_TTY=$(tty)' >> ~/.zprofile; fi\n```\n\n12. En caso de seguir con problemas seguir la siguiente secuencia:\n\n```\n    brew uninstall gpg\n    brew install gpg2\n    brew install pinentry-mac\n    gpg --full-generate-key\n```\n\n   * Obten la key generada:\n   \n```\n    gpg --list-keys\n```\n\nActualiza la key en local\n```\n   git config --global user.signingkey <Key de tu list>\n    git config --global gpg.program /usr/local/bin/gpg\n    git config --global commit.gpgsign true\n```\n\nExporta tu Key a GitHub :\n\n```\n    gpg --armor --export <key>\n```\n\nAgrega la key a GitHub desde GPG keys: \n\nSi el error a un persiste ejecuta el siguiente comando:\n\n```\n    test -r ~/.bash_profile && echo 'export GPG_TTY=$(tty)' >> ~/.bash_profile\n    echo 'export GPG_TTY=$(tty)' >> ~/.profile\n```\n\n*NOTA: Si el error aun persiste:\n\n   * *Instala:https://gpgtools.org*\n   * *Firma la clave que utilizaste presionando \"Sign\" en la barra de men: Key -> Sign*.\n\n## Generacin con Windows\n\n1. Correr el comando para verificar si ya existe alguna clave creada.\n```\n    gpg --list-secret-keys --keyid-format=long\n```\n2. Si no existe una clave se debe generar con el siguiente comando o en caso contrario pasar al paso 4):\n```\n    gpg --full-generate-key\n```\n  * Seleccionar el tipo de llave por defecto (RSA and RSA).\n  * Seleccionar la longitud de bits por defecto (3072).\n  * Seleccionar el tiempo de expiracin por defecto(0) y confirmar.\n  * Escribir tu nombre, correo electrnico, comentario opcional y Passhphrase y confirmarlos.\n\n4. Ejecutar el siguiente comando para visualizar la nueva llave existente:\n```\n    gpg --list-secret-keys --keyid-format=long\n```\n   * Copiar el Id de la clave: [ key_id ]\n   * Ejecutar el siguiente comando\n   \n```\n    gpg --armor --export [key_id]\n```\n   * Copiar la clave GPG, incluyendo comentarios\n   * Pegar la clave completa en https://github.com/settings/keys  e ingresa el ttulo deseado\n   * Ejecutar el comando con el ID de la clave GPG\n```\n    git config --global user.signingkey [ key_id ]\n```\n\n\nContact Support:\n Name: test\n Email: someemail@somedomain.com","type":"text/plain"}}}}
